eigentools/__init__.py
eigentools/criticalfinder.py
eigentools/eigenproblem.py
eigentools/tools.py
eigentools-2.2112.dist-info/METADATA
eigentools-2.2112.dist-info/WHEEL
eigentools-2.2112.dist-info/top_level.txt
eigentools-2.2112.dist-info/RECORD
