Metadata-Version: 2.1
Name: eigentools
Version: 2.2112
Summary: A toolkit for solving eigenvalue problems with Dedalus
Home-page: https://github.com/dedalusproject/eigentools
Author: J. S. Oishi
Author-email: jsoishi@gmail.com
License: UNKNOWN
Platform: UNKNOWN
Classifier: Programming Language :: Python :: 3
Classifier: License :: OSI Approved :: GNU General Public License v3 (GPLv3)
Requires-Python: >=3.5
